hmbp/__init__.py
hmbp/main.py
hmbp/tests/__init__.py
hmbp/tests/test_main.py
howmanyphotons-0.3.0.dist-info/LICENSE
howmanyphotons-0.3.0.dist-info/METADATA
howmanyphotons-0.3.0.dist-info/WHEEL
howmanyphotons-0.3.0.dist-info/RECORD
