Metadata-Version: 2.1
Name: HowManyPhotons
Version: 0.3.0
Summary: Simple photon count utility for astronomical fluxes
Home-page: https://github.com/AstarVienna/HowManyBloodyPhotons
License: GPLv3
Author: Kieran Leschinski
Author-email: kieran.leschinski@unive.ac.at
Maintainer: Kieran Leschinski
Maintainer-email: kieran.leschinski@unive.ac.at
Requires-Python: >=3.10,<3.13
Classifier: Intended Audience :: Science/Research
Classifier: License :: Other/Proprietary License
Classifier: Operating System :: OS Independent
Classifier: Programming Language :: Python :: 3
Classifier: Programming Language :: Python :: 3.10
Classifier: Programming Language :: Python :: 3.11
Classifier: Programming Language :: Python :: 3.12
Classifier: Topic :: Scientific/Engineering :: Astronomy
Requires-Dist: ScopeSim (>=0.9.3)
Requires-Dist: astropy (>=6.0.1,<7.0.0)
Requires-Dist: numpy (>=1.26.3,<2.0.0)
Requires-Dist: pyyaml (>=6.0.1,<7.0.0)
Requires-Dist: skycalc_ipy (>=0.5.2,<0.6.0)
Requires-Dist: synphot (>=1.4.0,<2.0.0)
Project-URL: Repository, https://github.com/AstarVienna/HowManyBloodyPhotons
